easyflow/__init__.py
easyflow/data/__init__.py
easyflow/data/mapper.py
easyflow/preprocessing/__init__.py
easyflow/preprocessing/base.py
easyflow/preprocessing/custom.py
easyflow/preprocessing/factory.py
easyflow/preprocessing/feature_preprocessor_layer.py
easyflow/preprocessing/pipeline.py
easyflow/tests/__init__.py
easyflow/tests/test_preprocessing.py
easy_tensorflow-1.5.0.dist-info/LICENSE
easy_tensorflow-1.5.0.dist-info/METADATA
easy_tensorflow-1.5.0.dist-info/WHEEL
easy_tensorflow-1.5.0.dist-info/top_level.txt
easy_tensorflow-1.5.0.dist-info/RECORD
