Metadata-Version: 2.1
Name: easy-tensorflow
Version: 1.5.0
Summary: Feature Pipelines for Keras preprocessing layers.
Home-page: https://github.com/fernandonieuwveldt/easyflow
Author: Fernando Nieuwveldt
Author-email: fdnieuwveldt@gmail.com
Classifier: Programming Language :: Python :: 3
Classifier: License :: OSI Approved :: MIT License
Classifier: Operating System :: OS Independent
Requires-Python: >=3.10
License-File: LICENSE
Requires-Dist: tensorflow >=2.16.1
